ibm_db_sa/__init__.py
ibm_db_sa/base.py
ibm_db_sa/ibm_db.py
ibm_db_sa/ibm_db_as400.py
ibm_db_sa/pyodbc.py
ibm_db_sa/reflection.py
ibm_db_sa/requirements.py
ibm_db_sa/zxjdbc.py
ibm_db_sa-0.4.3.dist-info/licenses/LICENSE
ibm_db_sa-0.4.3.dist-info/METADATA
ibm_db_sa-0.4.3.dist-info/WHEEL
ibm_db_sa-0.4.3.dist-info/entry_points.txt
ibm_db_sa-0.4.3.dist-info/top_level.txt
ibm_db_sa-0.4.3.dist-info/RECORD
