Metadata-Version: 2.4
Name: ibm_db_sa
Version: 0.4.3
Summary: SQLAlchemy support for IBM Data Servers
Home-page: http://pypi.python.org/pypi/ibm_db_sa/
Download-URL: https://github.com/ibmdb/python-ibmdbsa
Author: IBM Application Development Team
Author-email: balram.choudhary@ibm.com
License: Apache-2.0
Keywords: sqlalchemy database interface IBM Data Servers Db2
Platform: All
Classifier: Development Status :: 5 - Production/Stable
Classifier: Intended Audience :: Developers
Classifier: Operating System :: OS Independent
Classifier: Topic :: Database :: Front-Ends
License-File: LICENSE
Requires-Dist: sqlalchemy>=0.7.3
Requires-Dist: ibm_db>=2.0.0
Provides-Extra: dev
Requires-Dist: nose>=0.11; extra == "dev"
Dynamic: author
Dynamic: author-email
Dynamic: classifier
Dynamic: description
Dynamic: description-content-type
Dynamic: download-url
Dynamic: home-page
Dynamic: keywords
Dynamic: license
Dynamic: license-file
Dynamic: platform
Dynamic: provides-extra
Dynamic: requires-dist
Dynamic: summary
